Workbook

Sheet Modelo
A1: Quanto Custa Casar — simulador de faturação
A2: Legenda: texto azul com fundo amarelo = valores que pode alterar. Preto = fórmulas, não mexer.
A4: 1. Pressupostos por casal
A5: Valor médio do casamento (€) | B5: 35300
A6: Retalho que não passa por parceiros (€) — vestido, fato, alianças | B6: 3600
A7: Valor comissionável máximo por casal (€) | B7: =B5-B6
A8: Parte do comissionável contratada via parceiros (%) | B8: 0.53
A9: Valor contratado via parceiros por casal (€) | B9: =B7*B8
A10: Comissão sobre o valor contratado (%) | B10: 0.01
A11: Comissão por casal fechado (€) | B11: =B9*B10
A13: 2. Volume e campanhas (por mês)
A14: Casais fechados por mês | B14: 10
A15: Taxa de conversão de lead em casal fechado (%) | B15: 0.08
A16: Leads necessárias por mês | B16: =IF(B15>0,B14/B15,0)
A17: Custo por lead em anúncios (€) | B17: 5
A18: Custo mensal das campanhas (€) | B18: =B16*B17
A19: Custos fixos mensais (€) — Formspree, domínio, email, etc. | B19: 30
A21: 3. Resultado
A22: Faturação mensal em comissões (€) | B22: =B11*B14
A23: Faturação anual em comissões (€) | B23: =B22*12
A24: Custos mensais (campanhas + fixos) (€) | B24: =B18+B19
A25: Margem mensal (€) | B25: =B22-B24
A26: Margem anual (€) | B26: =B25*12
A27: Comissão mínima para as campanhas se pagarem (%) | B27: =IF(B9*B14>0,B24/(B9*B14),0)
A29: 4. Faturação mensal por comissão e por casais fechados (€)
A30: Comissão → casais fechados por mês | B30: 5 | C30: 10 | D30: 20 | E30: 30
A31: 0.01 | B31: =$B$9*$A31*B$30 | C31: =$B$9*$A31*C$30 | D31: =$B$9*$A31*D$30 | E31: =$B$9*$A31*E$30
A32: 0.02 | B32: =$B$9*$A32*B$30 | C32: =$B$9*$A32*C$30 | D32: =$B$9*$A32*D$30 | E32: =$B$9*$A32*E$30
A33: 0.03 | B33: =$B$9*$A33*B$30 | C33: =$B$9*$A33*C$30 | D33: =$B$9*$A33*D$30 | E33: =$B$9*$A33*E$30
A34: 0.05 | B34: =$B$9*$A34*B$30 | C34: =$B$9*$A34*C$30 | D34: =$B$9*$A34*D$30 | E34: =$B$9*$A34*E$30
A35: 0.08 | B35: =$B$9*$A35*B$30 | C35: =$B$9*$A35*C$30 | D35: =$B$9*$A35*D$30 | E35: =$B$9*$A35*E$30
A36: 0.1 | B36: =$B$9*$A36*B$30 | C36: =$B$9*$A36*C$30 | D36: =$B$9*$A36*D$30 | E36: =$B$9*$A36*E$30
A38: Margem mensal por comissão, com o volume e os custos da secção 2 (€)
A39: 0.01 | B39: =$B$9*$A39*$B$14-$B$24
A40: 0.02 | B40: =$B$9*$A40*$B$14-$B$24
A41: 0.03 | B41: =$B$9*$A41*$B$14-$B$24
A42: 0.05 | B42: =$B$9*$A42*$B$14-$B$24
A43: 0.08 | B43: =$B$9*$A43*$B$14-$B$24
A44: 0.1 | B44: =$B$9*$A44*$B$14-$B$24
A46: Nota: a sensibilidade usa o valor contratado por casal (B9) e, na margem, os custos da secção 2. O custo das campanhas não muda com a comissão.

Sheet Fluxo de caixa
A1: Fluxo de caixa a 24 meses
A2: A comissão só é recebida quando o fornecedor é pago — em regra perto do dia do casamento, muito depois do fecho.
A4: Meses entre o fecho e o recebimento da comissão | B4: 12
A5: Mês de arranque das campanhas | B5: 1
A7: Mês | B7: 1 | C7: 2 | D7: 3 | E7: 4 | F7: 5 | G7: 6 | H7: 7 | I7: 8 | J7: 9 | K7: 10 | L7: 11 | M7: 12 | N7: 13 | O7: 14 | P7: 15 | Q7: 16 | R7: 17 | S7: 18 | T7: 19 | U7: 20 | V7: 21 | W7: 22 | X7: 23 | Y7: 24
A8: Casais fechados | B8: =IF(B$7>=$B$5,Modelo!$B$14,0) | C8: =IF(C$7>=$B$5,Modelo!$B$14,0) | D8: =IF(D$7>=$B$5,Modelo!$B$14,0) | E8: =IF(E$7>=$B$5,Modelo!$B$14,0) | F8: =IF(F$7>=$B$5,Modelo!$B$14,0) | G8: =IF(G$7>=$B$5,Modelo!$B$14,0) | H8: =IF(H$7>=$B$5,Modelo!$B$14,0) | I8: =IF(I$7>=$B$5,Modelo!$B$14,0) | ... Y8: =IF(Y$7>=$B$5,Modelo!$B$14,0)
A9: Comissões geradas pelos fechos (€) | B9: =B8*Modelo!$B$11 | C9: =C8*Modelo!$B$11 | D9: =D8*Modelo!$B$11 | E9: =E8*Modelo!$B$11 | F9: =F8*Modelo!$B$11 | G9: =G8*Modelo!$B$11 | H9: =H8*Modelo!$B$11 | I9: =I8*Modelo!$B$11 | ... Y9: =Y8*Modelo!$B$11
A10: Comissões recebidas (€) | B10: =IF(B$7-$B$4>=1,INDEX($B$9:$Y$9,1,B$7-$B$4),0) | C10: =IF(C$7-$B$4>=1,INDEX($B$9:$Y$9,1,C$7-$B$4),0) | D10: =IF(D$7-$B$4>=1,INDEX($B$9:$Y$9,1,D$7-$B$4),0) | E10: =IF(E$7-$B$4>=1,INDEX($B$9:$Y$9,1,E$7-$B$4),0) | F10: =IF(F$7-$B$4>=1,INDEX($B$9:$Y$9,1,F$7-$B$4),0) | G10: =IF(G$7-$B$4>=1,INDEX($B$9:$Y$9,1,G$7-$B$4),0) | H10: =IF(H$7-$B$4>=1,INDEX($B$9:$Y$9,1,H$7-$B$4),0) | I10: =IF(I$7-$B$4>=1,INDEX($B$9:$Y$9,1,I$7-$B$4),0) | ... Y10: =IF(Y$7-$B$4>=1,INDEX($B$9:$Y$9,1,Y$7-$B$4),0)
A11: Custos (campanhas + fixos) (€) | B11: =IF(B$7>=$B$5,Modelo!$B$24,Modelo!$B$19) | C11: =IF(C$7>=$B$5,Modelo!$B$24,Modelo!$B$19) | D11: =IF(D$7>=$B$5,Modelo!$B$24,Modelo!$B$19) | E11: =IF(E$7>=$B$5,Modelo!$B$24,Modelo!$B$19) | F11: =IF(F$7>=$B$5,Modelo!$B$24,Modelo!$B$19) | G11: =IF(G$7>=$B$5,Modelo!$B$24,Modelo!$B$19) | H11: =IF(H$7>=$B$5,Modelo!$B$24,Modelo!$B$19) | I11: =IF(I$7>=$B$5,Modelo!$B$24,Modelo!$B$19) | ... Y11: =IF(Y$7>=$B$5,Modelo!$B$24,Modelo!$B$19)
A12: Saldo do mês (€) | B12: =B10-B11 | C12: =C10-C11 | D12: =D10-D11 | E12: =E10-E11 | F12: =F10-F11 | G12: =G10-G11 | H12: =H10-H11 | I12: =I10-I11 | ... Y12: =Y10-Y11
A13: Saldo acumulado (€) | B13: =B12 | C13: =B13+C12 | D13: =C13+D12 | E13: =D13+E12 | F13: =E13+F12 | G13: =F13+G12 | H13: =G13+H12 | I13: =H13+I12 | J13: =I13+J12 | ... Y13: =X13+Y12
A15: Total recebido em 24 meses (€) | B15: =SUM(B10:Y10)
A16: Total de custos em 24 meses (€) | B16: =SUM(B11:Y11)
A17: Comissões geradas mas ainda por receber no fim dos 24 meses (€) | B17: =SUM(B9:Y9)-B15
A18: Pior saldo acumulado — o fundo de maneio necessário (€) | B18: =MIN(B13:Y13)
